bobr_tools/__init__.py
bobr_tools/test.py
bobr_tools-0.1.0.dist-info/METADATA
bobr_tools-0.1.0.dist-info/WHEEL
bobr_tools-0.1.0.dist-info/top_level.txt
bobr_tools-0.1.0.dist-info/RECORD
